{
  "videos": [
    {
      "id": "VIDEO_ID_1",
      "title": "Did Life Come from Nothing? Atheist Student vs Cliffe Debate Gets Intense",
      "author": "Pastor Cliffe",
      "thumbnailUrl": "https://img.youtube.com/vi/0WAvFFiiF7g/hqdefault.jpg",
      "url": "https://www.youtube.com/embed/0WAvFFiiF7g",
      "version": "1"
    },
    {
      "id": "VIDEO_ID_2",
      "title": "Is God a Cosmic Dictator? Student Questions God’s Character, Cliffe Responds with Hard Truth",
      "author": "Pastor Cliffe",
      "thumbnailUrl": "https://img.youtube.com/vi/znjlMOE6k_U/hqdefault.jpg",
      "url": "https://www.youtube.com/embed/znjlMOE6k_U",
      "version": "1"
    },
    {
      "id": "VIDEO_ID_3",
      "title": "Why Did God Let Satan Torture Job? Student Confronts, Cliffe Delivers a Deep Answer",
      "author": "Pastor Cliffe",
      "thumbnailUrl": "https://img.youtube.com/vi/007RHtnTDtw/hqdefault.jpg",
      "url": "https://www.youtube.com/embed/007RHtnTDtw",
      "version": "1"
    },
    {
      "id": "VIDEO_ID_4",
      "title": "Student Asks: 'Why Didn’t God Just Skip to Heaven & Hell?' Cliffe Epic Reply Stuns Everyone",
      "author": "Pastor Cliffe",
      "thumbnailUrl": "https://img.youtube.com/vi/-dLI862lluo/hqdefault.jpg",
      "url": "https://www.youtube.com/embed/-dLI862lluo",
      "version": "1"
    },
    {
      "id": "VIDEO_ID_5",
      "title": "Atheist Student Insists ‘Belief = Reality’—Cliffe’s Epic Response Will Shock You!",
      "author": "Pastor Cliffe",
      "thumbnailUrl": "https://img.youtube.com/vi/AW2_7J39YGs/hqdefault.jpg",
      "url": "https://www.youtube.com/embed/AW2_7J39YGs",
      "version": "1"
    },
    {
      "id": "VIDEO_ID_6",
      "title": "‼️Cliffe Shuts Down Student’s Hope in Atheism with Epic Truth Bomb! Watch the Fireworks!",
      "author": "Pastor Cliffe",
      "thumbnailUrl": "https://img.youtube.com/vi/xp0R9pbndbY/hqdefault.jpg",
      "url": "https://www.youtube.com/embed/xp0R9pbndbY",
      "version": "1"
    },
    {
      "id": "VIDEO_ID_7",
      "title": "Atheist Misquotes the Bible—Pastor Cliffe Sets the Record Straight! Watch Now‼️",
      "author": "Pastor Cliffe",
      "thumbnailUrl": "https://img.youtube.com/vi/RKzMpGGt9ic/hqdefault.jpg",
      "url": "https://www.youtube.com/embed/RKzMpGGt9ic",
      "version": "1"
    },
    {
      "id": "VIDEO_ID_8",
      "title": "Muslim Student Claims Bible Contradicts Itself—Watch Pastor Cliffe’s Epic Masterclass Response!",
      "author": "Pastor Cliffe",
      "thumbnailUrl": "https://img.youtube.com/vi/0tZvxcWymXU/hqdefault.jpg",
      "url": "https://www.youtube.com/embed/0tZvxcWymXU",
      "version": "1"
    },
    {
      "id": "VIDEO_ID_9",
      "title": "Student Challenges Cliffe, 'Why Should We Believe In Jesus As God', Watch Cliffe Epic Response",
      "author": "Pastor Cliffe",
      "thumbnailUrl": "https://img.youtube.com/vi/oLOaH1i_PPk/hqdefault.jpg",
      "url": "https://www.youtube.com/embed/oLOaH1i_PPk",
      "version": "1"
    },
    {
      "id": "VIDEO_ID_10",
      "title": "Student Challenges Cliffe on Why Christianity Claims to Be the Only True Path to Heaven",
      "author": "Pastor Cliffe",
      "thumbnailUrl": "https://img.youtube.com/vi/hQ3N71hUDok/hqdefault.jpg",
      "url": "https://www.youtube.com/embed/hQ3N71hUDok",
      "version": "1"
    }
  ]
}